{
  "$schema": "https://raw.githubusercontent.com/spdx/spdx-spec/v2.2.1/schemas/spdx-schema.json",
  "spdxVersion": "SPDX-2.2",
  "dataLicense": "CC0-1.0",
  "SPDXID": "SPDXRef-DOCUMENT",
  "documentNamespace": "https://spdx.org/spdxdocs/boost-exception-x64-windows-1.85.0-3d9a2ea7-cc00-48b0-810d-d58145c23840",
  "name": "boost-exception:x64-windows@1.85.0 2908f38f33524778fbf0825b3cee1fa96bec5ba4dc8787513c4395354d4e8364",
  "creationInfo": {
    "creators": [
      "Tool: vcpkg-d6945642ee5c3076addd1a42c331bbf4cfc97457"
    ],
    "created": "2024-05-13T18:34:21Z"
  },
  "relationships": [
    {
      "spdxElementId": "SPDXRef-port",
      "relationshipType": "GENERATES",
      "relatedSpdxElement": "SPDXRef-binary"
    },
    {
      "spdxElementId": "SPDXRef-port",
      "relationshipType": "CONTAINS",
      "relatedSpdxElement": "SPDXRef-file-0"
    },
    {
      "spdxElementId": "SPDXRef-port",
      "relationshipType": "CONTAINS",
      "relatedSpdxElement": "SPDXRef-file-1"
    },
    {
      "spdxElementId": "SPDXRef-binary",
      "relationshipType": "GENERATED_FROM",
      "relatedSpdxElement": "SPDXRef-port"
    },
    {
      "spdxElementId": "SPDXRef-file-0",
      "relationshipType": "CONTAINED_BY",
      "relatedSpdxElement": "SPDXRef-port"
    },
    {
      "spdxElementId": "SPDXRef-file-1",
      "relationshipType": "CONTAINED_BY",
      "relatedSpdxElement": "SPDXRef-port"
    }
  ],
  "packages": [
    {
      "name": "boost-exception",
      "SPDXID": "SPDXRef-port",
      "versionInfo": "1.85.0",
      "downloadLocation": "git+https://github.com/Microsoft/vcpkg#ports/boost-exception",
      "homepage": "https://github.com/boostorg/exception",
      "licenseConcluded": "BSL-1.0",
      "licenseDeclared": "NOASSERTION",
      "copyrightText": "NOASSERTION",
      "description": "Boost exception module",
      "comment": "This is the port (recipe) consumed by vcpkg."
    },
    {
      "name": "boost-exception:x64-windows",
      "SPDXID": "SPDXRef-binary",
      "versionInfo": "2908f38f33524778fbf0825b3cee1fa96bec5ba4dc8787513c4395354d4e8364",
      "downloadLocation": "NONE",
      "licenseConcluded": "BSL-1.0",
      "licenseDeclared": "NOASSERTION",
      "copyrightText": "NOASSERTION",
      "comment": "This is a binary package built by vcpkg."
    },
    {
      "SPDXID": "SPDXRef-resource-1",
      "name": "boostorg/exception",
      "downloadLocation": "git+https://github.com/boostorg/exception@boost-1.85.0",
      "licenseConcluded": "NOASSERTION",
      "licenseDeclared": "NOASSERTION",
      "copyrightText": "NOASSERTION",
      "checksums": [
        {
          "algorithm": "SHA512",
          "checksumValue": "7ba040497aa0e0384a7e37df918baf2886735312a0e0f1406cf31568aad4f3d6b99cf38faa907cf7132b3f50905a071df5325d23c0a609ab8856371ba146b8ee"
        }
      ]
    }
  ],
  "files": [
    {
      "fileName": "./C:/Users/wesma/development/TavernLight/otclient/vcpkg/ports/boost-exception/portfile.cmake",
      "SPDXID": "SPDXRef-file-0",
      "checksums": [
        {
          "algorithm": "SHA256",
          "checksumValue": "d98167bbb071ffb81443fed888587c3a9c5c5455e412de8693ed1cba4ca203b0"
        }
      ],
      "licenseConcluded": "NOASSERTION",
      "copyrightText": "NOASSERTION"
    },
    {
      "fileName": "./C:/Users/wesma/development/TavernLight/otclient/vcpkg/ports/boost-exception/vcpkg.json",
      "SPDXID": "SPDXRef-file-1",
      "checksums": [
        {
          "algorithm": "SHA256",
          "checksumValue": "654bdacf2a561cfafbe159978bcd134280c6990d4387f7de570ff0392840ad82"
        }
      ],
      "licenseConcluded": "NOASSERTION",
      "copyrightText": "NOASSERTION"
    }
  ]
}
