{
  "$schema": "https://raw.githubusercontent.com/spdx/spdx-spec/v2.2.1/schemas/spdx-schema.json",
  "spdxVersion": "SPDX-2.2",
  "dataLicense": "CC0-1.0",
  "SPDXID": "SPDXRef-DOCUMENT",
  "documentNamespace": "https://spdx.org/spdxdocs/boost-variant-x64-windows-1.85.0-ea35542f-4075-4ac4-8edd-4784b381bcae",
  "name": "boost-variant:x64-windows@1.85.0 49f13de121986145d89889d810bd0dda1eded140da32601a8eb4a8ccfec4cebd",
  "creationInfo": {
    "creators": [
      "Tool: vcpkg-d6945642ee5c3076addd1a42c331bbf4cfc97457"
    ],
    "created": "2024-05-13T18:37:24Z"
  },
  "relationships": [
    {
      "spdxElementId": "SPDXRef-port",
      "relationshipType": "GENERATES",
      "relatedSpdxElement": "SPDXRef-binary"
    },
    {
      "spdxElementId": "SPDXRef-port",
      "relationshipType": "CONTAINS",
      "relatedSpdxElement": "SPDXRef-file-0"
    },
    {
      "spdxElementId": "SPDXRef-port",
      "relationshipType": "CONTAINS",
      "relatedSpdxElement": "SPDXRef-file-1"
    },
    {
      "spdxElementId": "SPDXRef-binary",
      "relationshipType": "GENERATED_FROM",
      "relatedSpdxElement": "SPDXRef-port"
    },
    {
      "spdxElementId": "SPDXRef-file-0",
      "relationshipType": "CONTAINED_BY",
      "relatedSpdxElement": "SPDXRef-port"
    },
    {
      "spdxElementId": "SPDXRef-file-1",
      "relationshipType": "CONTAINED_BY",
      "relatedSpdxElement": "SPDXRef-port"
    }
  ],
  "packages": [
    {
      "name": "boost-variant",
      "SPDXID": "SPDXRef-port",
      "versionInfo": "1.85.0",
      "downloadLocation": "git+https://github.com/Microsoft/vcpkg#ports/boost-variant",
      "homepage": "https://github.com/boostorg/variant",
      "licenseConcluded": "BSL-1.0",
      "licenseDeclared": "NOASSERTION",
      "copyrightText": "NOASSERTION",
      "description": "Boost variant module",
      "comment": "This is the port (recipe) consumed by vcpkg."
    },
    {
      "name": "boost-variant:x64-windows",
      "SPDXID": "SPDXRef-binary",
      "versionInfo": "49f13de121986145d89889d810bd0dda1eded140da32601a8eb4a8ccfec4cebd",
      "downloadLocation": "NONE",
      "licenseConcluded": "BSL-1.0",
      "licenseDeclared": "NOASSERTION",
      "copyrightText": "NOASSERTION",
      "comment": "This is a binary package built by vcpkg."
    },
    {
      "SPDXID": "SPDXRef-resource-1",
      "name": "boostorg/variant",
      "downloadLocation": "git+https://github.com/boostorg/variant@boost-1.85.0",
      "licenseConcluded": "NOASSERTION",
      "licenseDeclared": "NOASSERTION",
      "copyrightText": "NOASSERTION",
      "checksums": [
        {
          "algorithm": "SHA512",
          "checksumValue": "8d59963bb04fc72b1ac97c80fa0d8f72eb01118c4d5208312965c98293eccbf459f29aeaf0e62a9aa0a4407a13ccbb5bfffed16b34f1421b2a3bd8af800529eb"
        }
      ]
    }
  ],
  "files": [
    {
      "fileName": "./C:/Users/wesma/development/TavernLight/otclient/vcpkg/ports/boost-variant/portfile.cmake",
      "SPDXID": "SPDXRef-file-0",
      "checksums": [
        {
          "algorithm": "SHA256",
          "checksumValue": "1e61e579804a9ab51bf3eb89f9124a4989cea0ebf8825b0bffef9e0bbb3f19ca"
        }
      ],
      "licenseConcluded": "NOASSERTION",
      "copyrightText": "NOASSERTION"
    },
    {
      "fileName": "./C:/Users/wesma/development/TavernLight/otclient/vcpkg/ports/boost-variant/vcpkg.json",
      "SPDXID": "SPDXRef-file-1",
      "checksums": [
        {
          "algorithm": "SHA256",
          "checksumValue": "3db905f4448d9c394777e6826908e9328476e1d1f26b2b14052356faecf50e84"
        }
      ],
      "licenseConcluded": "NOASSERTION",
      "copyrightText": "NOASSERTION"
    }
  ]
}
